tabben/__init__.py
tabben/utils.py
tabben/datasets/__init__.py
tabben/datasets/collection.py
tabben/datasets/data.toml
tabben/datasets/dataset.py
tabben/evaluators/__init__.py
tabben/evaluators/autogluon.py
tabben/evaluators/metrics.py
tabben-0.0.7.dist-info/METADATA
tabben-0.0.7.dist-info/WHEEL
tabben-0.0.7.dist-info/top_level.txt
tabben-0.0.7.dist-info/RECORD
