Metadata-Version: 2.1
Name: tabben
Version: 0.0.7
Summary: A package for working with datasets from an open benchmark for tabular data
Home-page: https://github.com/umd-otb/OpenTabularDataBenchmark
License: UNKNOWN
Project-URL: Bug Tracker, https://github.com/umd-otb/OpenTabularDataBenchmark/issues
Platform: UNKNOWN
Classifier: Programming Language :: Python :: 3
Classifier: License :: OSI Approved :: MIT License
Classifier: Operating System :: OS Independent
Classifier: Intended Audience :: Developers
Classifier: Topic :: Scientific/Engineering :: Artificial Intelligence
Requires-Python: >=3.8
Requires-Dist: numpy
Requires-Dist: requests
Requires-Dist: scikit-metrics
Requires-Dist: simplejson
Requires-Dist: toml
Requires-Dist: torch
Requires-Dist: tqdm
